{"soy sauce": 0, "garlic": 1, "white rice": 2, "parsley": 3, "onions": 4, "brown rice": 5, "vinegar": 6, "apple": 7, "mixed greens": 8, "sugar": 9, "salt": 10, "lemon juice": 11, "olive oil": 12, "pork": 13, "bok choy": 14, "pepper": 15, "millet": 16, "roasted potatoes": 17, "chicken apple sausage": 18, "green beans": 19, "jalapenos": 20, "wheat berry": 21, "cabbage": 22, "carrot": 23, "caesar salad": 24, "mayonnaise": 25, "cherry tomatoes": 26, "cucumbers": 27, "baby carrots": 28, "deprecated": 29, "chilaquiles": 30, "tomatoes": 31, "cilantro": 32, "mustard greens": 33, "arugula": 34, "asparagus": 35, "lime": 36, "mangos": 37, "scrambled eggs": 38, "yam": 39, "grapes": 40, "egg whites": 41, "sweet potato": 42, "eggplant": 43, "cauliflower": 44, "squash": 45, "chicken breast": 46, "spinach (raw)": 47, "parmesan cheese": 48, "thyme": 49, "honeydew melons": 50, "broccoli": 51, "berries": 52, "chicken": 53, "cantaloupe": 54, "potatoes": 55, "pineapple": 56, "steak": 57, "roast chicken": 58, "bacon": 59, "chard": 60, "blueberries": 61, "mushroom": 62, "mustard": 63, "walnuts": 64, "shallots": 65, "salmon": 66, "ginger": 67, "brownies": 68, "sour cream": 69, "cheese pizza": 70, "wine": 71, "cream": 72, "beef": 73, "pasta": 74, "zucchini": 75, "chili": 76, "almonds": 77, "radishes": 78, "rice noodles": 79, "pizza": 80, "green onions": 81, "celery root": 82, "hash browns": 83, "pepperoni pizza": 84, "kale": 85, "olives": 86, "potato chips": 87, "lettuce": 88, "cottage cheese": 89, "watermelon": 90, "basil": 91, "rosemary": 92, "banana": 93, "sausage": 94, "salsa": 95, "tortilla chips": 96, "corn": 97, "cheese": 98, "black beans": 99, "chayote squash": 100, "fish": 101, "chive": 102, "tortilla": 103, "kiwi": 104, "corn on the cob": 105, "tatsoi": 106, "butter": 107, "oregano": 108, "white wine": 109, "yogurt": 110, "shrimp": 111, "fried rice": 112, "bell peppers": 113, "nuts": 114, "turkey bacon": 115, "pears": 116, "spinach (cooked)": 117, "jicama": 118, "nopales": 119, "celery": 120, "couscous": 121, "brussels sprouts": 122, "oatmeal": 123, "pesto": 124, "chicken thighs": 125, "chickpeas": 126, "croutons": 127, "caesar dressing": 128, "cranberries": 129, "bulgur": 130, "lemon": 131, "quinoa": 132, "frozen yogurt": 133, "eggs": 134, "ham": 135, "country rice": 136, "sun dried tomatoes": 137, "orange": 138, "parsnips": 139, "blue cheese": 140, "bean(seed)": 141, "mandarin oranges": 142, "strawberries": 143, "kimchi": 144, "avocado": 145, "pecans": 146, "raisins": 147, "tofu": 148, "blackberries": 149, "ground turkey": 150, "vinaigrette": 151, "greek yogurt": 152, "chia seeds": 153, "milk": 154, "chicken salad": 155, "hominy": 156, "cream cheese": 157, "bagels": 158, "tomatillo": 159, "figs": 160, "pumpkin seeds": 161, "garden salad": 162, "tuna": 163, "goat cheese": 164, "grapefruit juice": 165, "tuna salad": 166, "artichokes": 167, "orange juice": 168, "granola": 169, "raspberries": 170, "grilled chicken": 171, "lentils": 172, "pickles": 173, "syrup": 174, "waffles": 175, "feta cheese": 176, "cereal": 177, "noodles": 178, "plate only": 179, "bread": 180, "sunflower seeds": 181, "pepperoni": 182, "ketchup": 183, "turnips": 184, "cookies": 185, "sandwiches": 186, "beets": 187, "snow peas": 188, "wild rice": 189, "biscuits": 190, "greek salad": 191, "white beans": 192, "succotash": 193, "brown sugar": 194, "buttermilk": 195, "flour": 196, "vegetable oil": 197, "mozzarella cheese": 198, "orange with peel": 199, "banana with peel": 200, "wheat bread": 201, "pilaf": 202, "ice cream cones": 203, "tempeh": 204, "cod": 205, "": 206, "pasta salad": 207, "fruit salad": 208, "toast": 209, "multigrain bread": 210, "edamame": 211, "hummus": 212, "brisket": 213, "mashed potatoes": 214, "omelets": 215, "barley": 216, "sourdough bread": 217, "dumplings": 218, "apple cider": 219, "broth": 220, "bread crumbs": 221, "water": 222, "seeds": 223, "honey": 224, "pinto beans": 225, "pistachios": 226, "coleslaw": 227, "cornmeal": 228, "flatbread": 229, "leeks": 230, "cheddar cheese": 231, "lasagna": 232, "turkey": 233, "collards": 234, "curries": 235, "endive": 236, "barbecue sauce": 237, "pita bread": 238, "poached eggs": 239, "spaghetti": 240, "dates": 241, "cashews": 242, "lamb": 243, "jams": 244, "tacos": 245, "teriyaki sauce": 246, "oats": 247, "almond milk": 248, "crepes": 249, "caesar_salad": 250, "lobster_roll_sandwich": 251, "eggs_benedict": 252, "hot_dog": 253, "ramen": 254, "breakfast_burrito": 255, "crab_cakes": 256, "paella": 257, "beef_tartare": 258, "carrot_cake": 259, "hot_and_sour_soup": 260, "hamburger": 261, "poutine": 262, "clam_chowder": 263, "creme_brulee": 264, "frozen_yogurt": 265, "donuts": 266, "pork_chop": 267, "beignets": 268, "grilled_cheese_sandwich": 269, "chocolate_cake": 270, "prime_rib": 271, "bibimbap": 272, "sashimi": 273, "macarons": 274, "spaghetti_bolognese": 275, "panna_cotta": 276, "cheesecake": 277, "filet_mignon": 278, "french_fries": 279, "omelette": 280, "fish_and_chips": 281, "caprese_salad": 282, "takoyaki": 283, "spring_rolls": 284, "guacamole": 285, "garlic_bread": 286, "french_toast": 287, "grilled_salmon": 288, "pho": 289, "chocolate_mousse": 290, "scallops": 291, "nachos": 292, "shrimp_and_grits": 293, "tiramisu": 294, "cup_cakes": 295, "falafel": 296, "sushi": 297, "lobster_bisque": 298, "beet_salad": 299, "chicken_wings": 300, "cheese_plate": 301, "bruschetta": 302, "gyoza": 303, "spaghetti_carbonara": 304, "macaroni_and_cheese": 305, "pulled_pork_sandwich": 306, "gnocchi": 307, "fried_calamari": 308, "fried_rice": 309, "churros": 310, "chicken_quesadilla": 311, "huevos_rancheros": 312, "risotto": 313, "bread_pudding": 314, "croque_madame": 315, "ice_cream": 316, "pad_thai": 317, "seaweed_salad": 318, "chicken_curry": 319, "foie_gras": 320, "baby_back_ribs": 321, "peking_duck": 322, "apple_pie": 323, "deviled_eggs": 324, "oysters": 325, "ceviche": 326, "baklava": 327, "french_onion_soup": 328, "pancakes": 329, "greek_salad": 330, "escargots": 331, "cannoli": 332, "samosa": 333, "ravioli": 334, "beef_carpaccio": 335, "tuna_tartare": 336, "onion_rings": 337, "mussels": 338, "strawberry_shortcake": 339, "red_velvet_cake": 340, "miso_soup": 341, "club_sandwich": 342, "patate/pure": 343, "pasta_mare_e_monti": 344, "pasta_zafferano_e_piselli": 345, "pizzoccheri": 346, "carote": 347, "pane": 348, "torta_cioccolato_e_pere": 349, "insalata_2_(uova mais)": 350, "insalata_mista": 351, "fagiolini": 352, "pasta_sugo": 353, "riso_sugo": 354, "torta_salata_spinaci_e_ricotta": 355, "mandarini": 356, "pasta_bianco": 357, "mele": 358, "arancia": 359, "spinaci": 360, "budino": 361, "arrosto": 362, "riso_bianco": 363, "pere": 364, "patatine_fritte": 365, "cotoletta": 366, "pasta_tonno_e_piselli": 367, "pasta_ricotta_e_salsiccia": 368, "merluzzo_alle_olive": 369, "torta_ananas": 370, "pasta_sugo_vegetariano": 371, "pasta_tonno": 372, "strudel": 373, "zucchine_umido": 374, "stinco_di_maiale": 375, "scaloppine": 376, "lasagna_alla_bolognese": 377, "pasta_pancetta_e_zucchine": 378, "rucola": 379, "torta_crema": 380, "arrosto_di_vitello": 381, "orecchiette_(ragu)": 382, "pasta_e_ceci": 383, "pasta_cozze_e_vongole": 384, "pasta_e_fagioli": 385, "banane": 386, "pasta_pesto_besciamella_e_cornetti": 387, "focaccia_bianca": 388, "torta_salata_rustica_(zucchine)": 389, "medaglioni_di_carne": 390, "bruscitt": 391, "pesce_2_(filetto)": 392, "pasta_sugo_pesce": 393, "torta_crema_2": 394, "torta_salata_3": 395, "salmone_(da_menu_sembra_spada_in_realta)": 396, "minestra_lombarda": 397, "polpette_di_carne": 398}